xia_meta/__init__.py
xia_meta/asset.cp39-win_amd64.pyd
xia_meta/health.cp39-win_amd64.pyd
xia_meta/meta.cp39-win_amd64.pyd
xia_meta/tools.cp39-win_amd64.pyd
xia_meta-0.1.3.dist-info/LICENSE.txt
xia_meta-0.1.3.dist-info/METADATA
xia_meta-0.1.3.dist-info/WHEEL
xia_meta-0.1.3.dist-info/top_level.txt
xia_meta-0.1.3.dist-info/RECORD
