Metadata-Version: 2.1
Name: xia-meta
Version: 0.1.3
Summary: X-I-A Meta
Home-page: https://develop.x-i-a.com/docs/xia-meta/0.1.3/index.html
Author: X-I-A
Author-email: admin@x-i-a.com
License: UNKNOWN
Platform: UNKNOWN
Requires-Python: >=3.9
License-File: LICENSE.txt
Requires-Dist: xia-engine-firestore
